topsis_pack_3185/cli.py
topsis_pack_3185/example.py
topsis_3185-1.0.1.dist-info/LICENSE
topsis_3185-1.0.1.dist-info/METADATA
topsis_3185-1.0.1.dist-info/WHEEL
topsis_3185-1.0.1.dist-info/entry_points.txt
topsis_3185-1.0.1.dist-info/top_level.txt
topsis_3185-1.0.1.dist-info/RECORD
